{ 
    
    "player": [
        
        {
            "density": 2, "friction": 0, "bounce": 0, 
            "filter": { "categoryBits": 1, "maskBits": 65535 },
            "shape": [   46, 90  ,  103, 36  ,  113, 36  ,  103, 76  ,  69, 109  ,  50, 111  ]
        } ,
        {
            "density": 2, "friction": 0, "bounce": 0, 
            "filter": { "categoryBits": 1, "maskBits": 65535 },
            "shape": [   34, 47  ,  103, 36  ,  39, 69  ,  21, 54  ]
        } ,
        {
            "density": 2, "friction": 0, "bounce": 0, 
            "filter": { "categoryBits": 1, "maskBits": 65535 },
            "shape": [   67, 0  ,  103, 36  ,  46, 22  ,  49, 2  ]
        } ,
        {
            "density": 2, "friction": 0, "bounce": 0, 
            "filter": { "categoryBits": 1, "maskBits": 65535 },
            "shape": [   146, 69  ,  103, 76  ,  113, 36  ,  146, 43  ]
        } ,
        {
            "density": 2, "friction": 0, "bounce": 0, 
            "filter": { "categoryBits": 1, "maskBits": 65535 },
            "shape": [   0, 28  ,  46, 22  ,  103, 36  ,  34, 47  ,  0, 36  ]
        } ,
        {
            "density": 2, "friction": 0, "bounce": 0, 
            "filter": { "categoryBits": 1, "maskBits": 65535 },
            "shape": [   39, 69  ,  46, 90  ,  0, 83  ,  0, 75  ]
        } ,
        {
            "density": 2, "friction": 0, "bounce": 0, 
            "filter": { "categoryBits": 1, "maskBits": 65535 },
            "shape": [   103, 36  ,  46, 90  ,  39, 69  ]
        }
    ]
}
